DigitalizationTools/__init__.py
DigitalizationTools/api.py
DigitalizationTools/components.py
DigitalizationTools/mongodb_api.py
DigitalizationTools/postgresql_api.py
DigitalizationTools/sqlite3_api.py
DigitalizationTools-0.2.7.dist-info/LICENSE
DigitalizationTools-0.2.7.dist-info/METADATA
DigitalizationTools-0.2.7.dist-info/WHEEL
DigitalizationTools-0.2.7.dist-info/top_level.txt
DigitalizationTools-0.2.7.dist-info/RECORD
