Metadata-Version: 2.1
Name: DigitalizationTools
Version: 0.2.7
Summary: A package that manages database through PostgreSQL and creates webapp through Dash plotly.
Author: Mengke Lu
Author-email: <mklu0611@gmail.com>
Keywords: python,postgresql,dash
Classifier: Development Status :: 1 - Planning
Classifier: Intended Audience :: Developers
Classifier: Programming Language :: Python :: 3
Classifier: Operating System :: Unix
Classifier: Operating System :: MacOS :: MacOS X
Classifier: Operating System :: Microsoft :: Windows
License-File: LICENSE
